ramage-0.1.0.dist-info/METADATA
ramage-0.1.0.dist-info/WHEEL
ramage/__init__.py
ramage/__init__.pyi
ramage/py.typed
ramage/ramage.cpython-311-i386-linux-gnu.so
ramage-0.1.0.dist-info/RECORD
